{"version":1,"resource":"file:///home/tariqul/Projects/tools-hub/components/tools/url/link-expand-client.tsx","entries":[{"id":"AzXh.tsx","timestamp":1756708308698},{"id":"vdWQ.tsx","timestamp":1756708359723},{"id":"EUHP.tsx","timestamp":1756708371748},{"id":"9w3A.tsx","timestamp":1756708386250},{"id":"epJ1.tsx","timestamp":1756708407154},{"id":"DKT6.tsx","timestamp":1756708440546},{"id":"iu90.tsx","timestamp":1756708466958},{"id":"4ilq.tsx","timestamp":1756708488046},{"id":"AlBJ.tsx","timestamp":1756708515989},{"id":"ZZtL.tsx","timestamp":1756708656056},{"id":"t6IK.tsx","timestamp":1756708669666},{"id":"CONS.tsx","timestamp":1756708702683},{"id":"MW1M.tsx","source":"Organize Imports","timestamp":1756708707832},{"id":"FedT.tsx","timestamp":1756708763196},{"id":"miWY.tsx","timestamp":1756708778024},{"id":"aee7.tsx","timestamp":1756708828234},{"id":"CJZT.tsx","timestamp":1756708965826},{"id":"Tgfb.tsx","timestamp":1756708996257},{"id":"w4Z9.tsx","source":"undoRedo.source","timestamp":1756709042587},{"id":"38ET.tsx","timestamp":1756709065792},{"id":"EEeD.tsx","timestamp":1756709077832},{"id":"D8Mt.tsx","source":"undoRedo.source","timestamp":1756709086276},{"id":"TODq.tsx","timestamp":1756709091069},{"id":"EI14.tsx","timestamp":1756709137238},{"id":"CJuW.tsx","timestamp":1756709189464},{"id":"5UkF.tsx","timestamp":1756709247759},{"id":"kWhD.tsx","timestamp":1756836819164},{"id":"70sw.tsx","timestamp":1756895329019},{"id":"GAHF.tsx","timestamp":1756905381963},{"id":"06On.tsx","timestamp":1756905396440},{"id":"yUkN.tsx","timestamp":1756916659243},{"id":"E3JW.tsx","timestamp":1756916695087},{"id":"pE2q.tsx","timestamp":1756916729918},{"id":"McG9.tsx","timestamp":1756916751221},{"id":"GTEV.tsx","source":"Apply all safe fixes (Biome)","timestamp":1756916810240},{"id":"l7aC.tsx","timestamp":1756916817975},{"id":"EJFe.tsx","timestamp":1756916828227},{"id":"sfir.tsx","source":"undoRedo.source","timestamp":1756916837139},{"id":"bNxe.tsx","timestamp":1756916845883},{"id":"WoPn.tsx","timestamp":1756917185320},{"id":"Q2EN.tsx","timestamp":1756917207795},{"id":"H9u6.tsx","timestamp":1756917240518},{"id":"uGvR.tsx","timestamp":1756917286783},{"id":"1HHt.tsx","timestamp":1756917395462},{"id":"eCH2.tsx","source":"searchReplace.source","timestamp":1757245857382},{"id":"ZuS2.tsx","source":"searchReplace.source","timestamp":1757252945393},{"id":"0MFt.tsx","timestamp":1757582166490},{"id":"7TpE.tsx","timestamp":1757582183416},{"id":"NPY9.tsx","source":"Workspace Edit","timestamp":1757582207634},{"id":"pd9e.tsx","source":"Workspace Edit","timestamp":1757590302567}]}