{"version":1,"resource":"file:///home/tariqul/Projects/tools-hub/components/tools/time/countdown-timer-client.tsx","entries":[{"id":"VRiu.tsx","timestamp":1756873772201},{"id":"RhxI.tsx","timestamp":1756873794839},{"id":"YtJH.tsx","timestamp":1756873810525},{"id":"DOmj.tsx","timestamp":1756873865289},{"id":"Q6KK.tsx","timestamp":1756873900932},{"id":"2Uri.tsx","timestamp":1756873930352},{"id":"OpVO.tsx","timestamp":1756873969275},{"id":"pHyR.tsx","timestamp":1756873981231},{"id":"34hL.tsx","timestamp":1756874003018},{"id":"YquQ.tsx","timestamp":1756874017694},{"id":"TimY.tsx","timestamp":1756874041183},{"id":"yDee.tsx","timestamp":1756874051940},{"id":"vvjp.tsx","timestamp":1756874076328},{"id":"ssBK.tsx","timestamp":1756874117207},{"id":"Npn9.tsx","timestamp":1756874132218},{"id":"xoro.tsx","timestamp":1756874163538},{"id":"kklx.tsx","timestamp":1756874198167},{"id":"GDr9.tsx","timestamp":1756874226435},{"id":"Rk9n.tsx","source":"undoRedo.source","timestamp":1756874232909},{"id":"HZfg.tsx","timestamp":1756874240940},{"id":"M05s.tsx","timestamp":1756877311512},{"id":"DmYd.tsx","timestamp":1756895833157},{"id":"5iUC.tsx","timestamp":1756895892422},{"id":"FF2Y.tsx","timestamp":1756895902637},{"id":"bEVs.tsx","timestamp":1756895931293},{"id":"yBkv.tsx","timestamp":1756896025660},{"id":"epKy.tsx","timestamp":1756965703245},{"id":"YXKi.tsx","timestamp":1756965718806},{"id":"eGrl.tsx","timestamp":1756965809729},{"id":"TqXb.tsx","timestamp":1756965822623},{"id":"m6Sr.tsx","timestamp":1756965849772},{"id":"6v9v.tsx","timestamp":1756965870324},{"id":"pFxj.tsx","timestamp":1756965901887},{"id":"Sm8I.tsx","timestamp":1756966005142},{"id":"6vGK.tsx","timestamp":1756966096183},{"id":"ZgRO.tsx","timestamp":1756966207846},{"id":"AYnN.tsx","source":"Workspace Edit","timestamp":1756966244068},{"id":"hT23.tsx","timestamp":1756966250998},{"id":"6HGR.tsx","timestamp":1756966261384},{"id":"y5te.tsx","timestamp":1756966279624},{"id":"YWE6.tsx","timestamp":1756966290925},{"id":"XQz7.tsx","timestamp":1756966307289},{"id":"IuCv.tsx","source":"searchReplace.source","timestamp":1757245855042},{"id":"NAeI.tsx","source":"searchReplace.source","timestamp":1757252945395},{"id":"R7cS.tsx","source":"undoRedo.source","timestamp":1757516867647},{"id":"kKkz.tsx","timestamp":1757516874314},{"id":"iGXg.tsx","source":"undoRedo.source","timestamp":1757516891775},{"id":"6DuM.tsx","source":"Workspace Edit","timestamp":1757610667421},{"id":"rIVn.tsx","source":"Workspace Edit","timestamp":1757610844319},{"id":"NxRP.tsx","source":"Workspace Edit","timestamp":1757610913455}]}