{"version":1,"resource":"file:///home/tariqul/Projects/tools-hub/lib/utils.ts","entries":[{"id":"3k6M.ts","timestamp":1757586198955},{"id":"oXtY.ts","timestamp":1757586286556},{"id":"EJHN.ts","timestamp":1757586418095},{"id":"f2fm.ts","timestamp":1757586640456},{"id":"3P9C.ts","timestamp":1757586726454},{"id":"F8y0.ts","timestamp":1757586987026},{"id":"I2UU.ts","timestamp":1757587143013},{"id":"GW9y.ts","timestamp":1757588078355},{"id":"yEg6.ts","timestamp":1757588095128},{"id":"3Jfe.ts","timestamp":1757588517215},{"id":"2IPm.ts","timestamp":1757588549869},{"id":"8z0G.ts","timestamp":1757588625794},{"id":"6vm3.ts","timestamp":1757588652225},{"id":"ZiY7.ts","timestamp":1757610636197},{"id":"02Ba.ts","timestamp":1757610820303},{"id":"Kbnl.ts","timestamp":1757610891603},{"id":"sMWl.ts","timestamp":1757610968777},{"id":"qPoz.ts","timestamp":1757611056509},{"id":"MFD8.ts","timestamp":1757611125285},{"id":"ohfl.ts","timestamp":1757611139151},{"id":"xu6f.ts","timestamp":1757611180509},{"id":"aSRu.ts","timestamp":1757611228158},{"id":"DMTL.ts","timestamp":1757825629065}]}