{"version":1,"resource":"file:///home/tariqul/Projects/tools-hub/app/tools/%28tools%29/url/expand/page.tsx","entries":[{"id":"ZT7O.tsx","timestamp":1756621211295},{"id":"tJV3.tsx","timestamp":1756626573877},{"id":"oaSF.tsx","timestamp":1756702971245},{"id":"NrNa.tsx","timestamp":1756703091699},{"id":"pdib.tsx","timestamp":1756703179784},{"id":"i3k6.tsx","timestamp":1756703210596},{"id":"EUGH.tsx","timestamp":1756703226108},{"id":"nfvo.tsx","timestamp":1756703250454},{"id":"lOuh.tsx","timestamp":1756703286306},{"id":"7wLR.tsx","source":"Organize Imports","timestamp":1756703307138},{"id":"GgbR.tsx","source":"Workspace Edit","timestamp":1756703389123},{"id":"wi2n.tsx","timestamp":1756703390970},{"id":"qgJo.tsx","timestamp":1756703407658},{"id":"kwcJ.tsx","timestamp":1756703433274},{"id":"K9li.tsx","timestamp":1756703453755},{"id":"P6t5.tsx","timestamp":1756703468872},{"id":"Xi0h.tsx","timestamp":1756703522081},{"id":"zZFE.tsx","timestamp":1756703609590},{"id":"V0V0.tsx","timestamp":1756703634909},{"id":"WYzp.tsx","timestamp":1756703652097},{"id":"1d8G.tsx","timestamp":1756703668448},{"id":"1Erh.tsx","timestamp":1756703683589},{"id":"v5Ob.tsx","timestamp":1756703696906},{"id":"eyAp.tsx","timestamp":1756703708362},{"id":"hByX.tsx","timestamp":1756703806038},{"id":"3t87.tsx","timestamp":1756703816487},{"id":"1Iz6.tsx","timestamp":1756703828808},{"id":"5lxI.tsx","timestamp":1756703839483},{"id":"seZL.tsx","timestamp":1756703871803},{"id":"xlqA.tsx","timestamp":1756703904966},{"id":"hsXY.tsx","timestamp":1756703930308},{"id":"vzQC.tsx","timestamp":1756703942291},{"id":"THkY.tsx","source":"searchReplace.source","timestamp":1756706048243},{"id":"ZWzo.tsx","source":"Organize Imports","timestamp":1756707427746},{"id":"kQXJ.tsx","timestamp":1756707450498},{"id":"SYk9.tsx","source":"Workspace Edit","timestamp":1756707639573},{"id":"iyYD.tsx","timestamp":1756723320994},{"id":"fQxa.tsx","timestamp":1756905648805},{"id":"e9jm.tsx","timestamp":1756906518085},{"id":"zCZj.tsx","timestamp":1757601821676},{"id":"5W9b.tsx","timestamp":1757601831692},{"id":"pznu.tsx","timestamp":1757601856542},{"id":"zNG3.tsx","timestamp":1757601983348},{"id":"dibS.tsx","timestamp":1757602306677},{"id":"mXjI.tsx","timestamp":1757602769382},{"id":"c3uA.tsx","timestamp":1757609832357},{"id":"YzRo.tsx","timestamp":1757609852002},{"id":"xH0R.tsx","timestamp":1757609871352},{"id":"kEnj.tsx","source":"searchReplace.source","timestamp":1757670185871}]}