{"version":1,"resource":"file:///home/tariqul/Projects/Portfolio/portfolio-next/models/project.model.ts","entries":[{"id":"Fjn5.ts","source":"Workspace Edit","timestamp":1753592723638},{"id":"z6yl.ts","timestamp":1753592743662},{"id":"LmVX.ts","timestamp":1753592780842},{"id":"Z3OS.ts","source":"undoRedo.source","timestamp":1753592790811},{"id":"WDd6.ts","timestamp":1753592806825},{"id":"Oatd.ts","timestamp":1753593013170},{"id":"KYUm.ts","source":"undoRedo.source","timestamp":1753593022155},{"id":"QPXF.ts","timestamp":1753593120511},{"id":"jyLg.ts","timestamp":1753593274682},{"id":"1uQ7.ts","timestamp":1753593470096},{"id":"ocLc.ts","timestamp":1753593588476},{"id":"IhTw.ts","source":"Organize Imports","timestamp":1753593767626},{"id":"2FxT.ts","timestamp":1753593779374},{"id":"5jlh.ts","timestamp":1753593794256},{"id":"r9Xh.ts","source":"Organize Imports","timestamp":1753593813963},{"id":"cEWU.ts","source":"Organize Imports","timestamp":1753594343506},{"id":"Hqm4.ts","timestamp":1753594406508},{"id":"DOGk.ts","source":"Workspace Edit","timestamp":1753594412395},{"id":"H4Ie.ts","timestamp":1753594425855},{"id":"ylkv.ts","timestamp":1753594522319},{"id":"4zuM.ts","timestamp":1753594564041},{"id":"g9Ye.ts","timestamp":1753595049559},{"id":"lnKe.ts","timestamp":1753595073852},{"id":"FwN1.ts","source":"Workspace Edit","timestamp":1753595097832},{"id":"KCaW.ts","timestamp":1753595317963},{"id":"xTmL.ts","timestamp":1753595329018},{"id":"DwYy.ts","source":"Workspace Edit","timestamp":1753595335114},{"id":"owVl.ts","timestamp":1753595837846},{"id":"YDIO.ts","timestamp":1753596266211},{"id":"DaCX.ts","timestamp":1753596384030},{"id":"dqv5.ts","timestamp":1753596515273},{"id":"BZDi.ts","timestamp":1753688477997},{"id":"R62y.ts","timestamp":1753694028246},{"id":"o212.ts","timestamp":1753694460797},{"id":"d0x2.ts","timestamp":1753695025371},{"id":"qJdC.ts","timestamp":1753936043897},{"id":"KuyZ.ts","timestamp":1753936164016},{"id":"lioP.ts","timestamp":1755352454710},{"id":"24ln.ts","timestamp":1755353934610},{"id":"hwWc.ts","source":"Organize Imports","timestamp":1755354417390}]}