{"version":1,"resource":"file:///home/tariqul/Projects/natural-sefa-v2/components/global/future-placeholder.tsx","entries":[{"id":"7gWe.tsx","source":"Apply all safe fixes (Biome)","timestamp":1758908850432},{"id":"w1AJ.tsx","source":"Apply all safe fixes (Biome)","timestamp":1758909195058},{"id":"Z21u.tsx","source":"Renaming FuturePlaceholderMuted to FuturePlaceholder","timestamp":1758909226378},{"id":"DU64.tsx","timestamp":1758909289559},{"id":"oLRH.tsx","source":"Workspace Edit","timestamp":1758909335852},{"id":"iT11.tsx","timestamp":1758909347325},{"id":"l5CH.tsx","timestamp":1758909441615},{"id":"mpAC.tsx","timestamp":1758909465758},{"id":"bcFR.tsx","timestamp":1758937557866}]}