{"version":1,"resource":"file:///home/tariqul/Projects/Portfolio/portfolio-next/app/%28dashboard%29/admin/layout.tsx","entries":[{"id":"KxJ1.tsx","timestamp":1753615056296},{"id":"kQvT.tsx","timestamp":1753615074634},{"id":"5hg9.tsx","timestamp":1753615101466},{"id":"BPTF.tsx","timestamp":1753615122513},{"id":"kEqh.tsx","timestamp":1753615141255},{"id":"CbzA.tsx","timestamp":1753615153502},{"id":"Jnqq.tsx","timestamp":1753615180328},{"id":"eQns.tsx","timestamp":1753615195689},{"id":"7T9l.tsx","timestamp":1753615212662},{"id":"L6aY.tsx","timestamp":1753615318071},{"id":"ixdV.tsx","timestamp":1753615346496},{"id":"zj9H.tsx","timestamp":1753615364067},{"id":"xVpq.tsx","timestamp":1753615428436},{"id":"FXU9.tsx","timestamp":1753615440291},{"id":"l8tq.tsx","timestamp":1753622658464},{"id":"xzW8.tsx","timestamp":1753622962031},{"id":"spG5.tsx","source":"Workspace Edit","timestamp":1753623308662},{"id":"CjGr.tsx","timestamp":1753623355968},{"id":"fvWA.tsx","timestamp":1753623374865},{"id":"tXXp.tsx","timestamp":1753625558663},{"id":"KtPG.tsx","timestamp":1753625570230},{"id":"DzTf.tsx","timestamp":1753625890063}]}